ooga_booga-0.1.0.dist-info/licenses/LICENSE
ooga_booga_encryption/__init__.py
ooga_booga_encryption/encryption.py
ooga_booga-0.1.0.dist-info/METADATA
ooga_booga-0.1.0.dist-info/WHEEL
ooga_booga-0.1.0.dist-info/top_level.txt
ooga_booga-0.1.0.dist-info/RECORD
