Metadata-Version: 2.4
Name: ooga-booga
Version: 0.1.0
Summary: A fun encryption module that converts Python data into 'ooga booga' style words.
Author: Your Name
Author-email: Your Name <your.email@example.com>
License: MIT License
Project-URL: Homepage, https://github.com/yourusername/ooga-booga
Classifier: Programming Language :: Python :: 3
Classifier: License :: OSI Approved :: MIT License
Classifier: Operating System :: OS Independent
Requires-Python: >=3.6
License-File: LICENSE
Dynamic: license-file
